{
  "payments": [
    {
      "id": "payment_001",
      "bookingId": "booking_001",
      "transactionId": "TXN_WED_001_2024",
      "employerId": "employer_001",
      "employerName": "Rahul Sharma",
      "freelancerId": "freelancer_001",
      "freelancerName": "Rajesh Kumar",
      "serviceName": "Wedding Chef Service",
      "serviceCategory": "Chef",
      "amount": 8000,
      "totalBookingAmount": 25000,
      "paymentType": "advance",
      "paymentMethod": "UPI",
      "paymentStatus": "completed",
      "platformFee": 800,
      "processingFee": 50,
      "taxes": 144,
      "netAmount": 7006,
      "paymentDate": "2024-02-12T15:30:00Z",
      "bookingDate": "2024-02-15",
      "location": "Meerut, UP",
      "paymentGateway": "Razorpay",
      "gatewayTransactionId": "rzp_001_wedding_chef",
      "refundStatus": null,
      "description": "Advance payment for wedding catering service"
    },
    {
      "id": "payment_002",
      "bookingId": "booking_002",
      "transactionId": "TXN_CORP_002_2024",
      "employerId": "employer_002",
      "employerName": "Tech Solutions Pvt Ltd",
      "freelancerId": "freelancer_006",
      "freelancerName": "Anita Reddy",
      "serviceName": "Corporate Event Bartending",
      "serviceCategory": "Bartender",
      "amount": 12000,
      "totalBookingAmount": 12000,
      "paymentType": "full",
      "paymentMethod": "Credit Card",
      "paymentStatus": "completed",
      "platformFee": 1200,
      "processingFee": 75,
      "taxes": 216,
      "netAmount": 10509,
      "paymentDate": "2024-02-15T12:45:00Z",
      "bookingDate": "2024-02-20",
      "location": "Bangalore, Karnataka",
      "paymentGateway": "Stripe",
      "gatewayTransactionId": "strp_002_bartender",
      "refundStatus": null,
      "description": "Full payment for corporate bartending service"
    },
    {
      "id": "payment_003",
      "bookingId": "booking_003",
      "transactionId": "TXN_DJ_003_2024",
      "employerId": "employer_003",
      "employerName": "Priya & Amit",
      "freelancerId": "freelancer_011",
      "freelancerName": "Sunil Yadav",
      "serviceName": "Wedding DJ & Music",
      "serviceCategory": "DJ",
      "amount": 6000,
      "totalBookingAmount": 18000,
      "paymentType": "advance",
      "paymentMethod": "Net Banking",
      "paymentStatus": "completed",
      "platformFee": 600,
      "processingFee": 40,
      "taxes": 108,
      "netAmount": 5252,
      "paymentDate": "2024-02-18T16:20:00Z",
      "bookingDate": "2024-02-25",
      "location": "Hyderabad, Telangana",
      "paymentGateway": "Razorpay",
      "gatewayTransactionId": "rzp_003_dj_wedding",
      "refundStatus": null,
      "description": "Advance payment for wedding DJ service"
    },
    {
      "id": "payment_004",
      "bookingId": "booking_005",
      "transactionId": "TXN_MAGIC_005_2024",
      "employerId": "employer_005",
      "employerName": "Sunita Gupta",
      "freelancerId": "freelancer_021",
      "freelancerName": "Vivek Pandey",
      "serviceName": "Birthday Party Magic Show",
      "serviceCategory": "Magician",
      "amount": 1000,
      "totalBookingAmount": 3500,
      "paymentType": "advance",
      "paymentMethod": "Debit Card",
      "paymentStatus": "completed",
      "platformFee": 100,
      "processingFee": 25,
      "taxes": 18,
      "netAmount": 857,
      "paymentDate": "2024-03-02T10:30:00Z",
      "bookingDate": "2024-03-10",
      "location": "Noida, UP",
      "paymentGateway": "PayU",
      "gatewayTransactionId": "payu_005_magic_show",
      "refundStatus": null,
      "description": "Advance payment for birthday magic show"
    },
    {
      "id": "payment_005",
      "bookingId": "booking_008",
      "transactionId": "TXN_DECOR_008_2024",
      "employerId": "employer_008",
      "employerName": "Rohit & Family",
      "freelancerId": "freelancer_035",
      "freelancerName": "Arjun Desai",
      "serviceName": "Birthday Theme Decoration",
      "serviceCategory": "Theme Decorator",
      "amount": 4000,
      "totalBookingAmount": 12000,
      "paymentType": "advance",
      "paymentMethod": "UPI",
      "paymentStatus": "completed",
      "platformFee": 400,
      "processingFee": 30,
      "taxes": 72,
      "netAmount": 3498,
      "paymentDate": "2024-03-17T14:20:00Z",
      "bookingDate": "2024-03-25",
      "location": "Mumbai, Maharashtra",
      "paymentGateway": "Razorpay",
      "gatewayTransactionId": "rzp_008_decoration",
      "refundStatus": null,
      "description": "Advance payment for birthday decoration"
    },
    {
      "id": "payment_006",
      "bookingId": "booking_006",
      "transactionId": "TXN_COMEDY_006_2024",
      "employerId": "employer_006",
      "employerName": "Marketing Hub Ltd",
      "freelancerId": "freelancer_026",
      "freelancerName": "Sunita Devi",
      "serviceName": "Corporate Comedy Night",
      "serviceCategory": "Stand-up Comedian",
      "amount": 8000,
      "totalBookingAmount": 8000,
      "paymentType": "full",
      "paymentMethod": "Credit Card",
      "paymentStatus": "refunded",
      "platformFee": 800,
      "processingFee": 50,
      "taxes": 144,
      "netAmount": 7006,
      "paymentDate": "2024-03-05T13:00:00Z",
      "bookingDate": "2024-03-15",
      "location": "Ranchi, Jharkhand",
      "paymentGateway": "Stripe",
      "gatewayTransactionId": "strp_006_comedy",
      "refundStatus": "refunded",
      "refundDate": "2024-03-08T11:30:00Z",
      "refundAmount": 8000,
      "refundReason": "Event cancelled by client",
      "description": "Full payment for corporate comedy show - REFUNDED"
    },
    {
      "id": "payment_007",
      "bookingId": "booking_007",
      "transactionId": "TXN_MEHENDI_007_2024",
      "employerId": "employer_007",
      "employerName": "Kavita Mehta",
      "freelancerId": "freelancer_033",
      "freelancerName": "Sita Gupta",
      "serviceName": "Bridal Mehendi Design",
      "serviceCategory": "Mehendi Artist",
      "amount": 5000,
      "totalBookingAmount": 5000,
      "paymentType": "cash_on_delivery",
      "paymentMethod": "Cash",
      "paymentStatus": "completed",
      "platformFee": 0,
      "processingFee": 0,
      "taxes": 0,
      "netAmount": 5000,
      "paymentDate": "2024-03-20T18:30:00Z",
      "bookingDate": "2024-03-20",
      "location": "Jaipur, Rajasthan",
      "paymentGateway": null,
      "gatewayTransactionId": null,
      "refundStatus": null,
      "description": "Cash payment for bridal mehendi service"
    },
    {
      "id": "payment_008",
      "bookingId": "booking_001_remaining",
      "transactionId": "TXN_WED_001_REM_2024",
      "employerId": "employer_001",
      "employerName": "Rahul Sharma",
      "freelancerId": "freelancer_001",
      "freelancerName": "Rajesh Kumar",
      "serviceName": "Wedding Chef Service",
      "serviceCategory": "Chef",
      "amount": 17000,
      "totalBookingAmount": 25000,
      "paymentType": "remaining",
      "paymentMethod": "UPI",
      "paymentStatus": "pending",
      "platformFee": 1700,
      "processingFee": 85,
      "taxes": 306,
      "netAmount": 14909,
      "paymentDate": null,
      "bookingDate": "2024-02-15",
      "location": "Meerut, UP",
      "paymentGateway": "Razorpay",
      "gatewayTransactionId": null,
      "refundStatus": null,
      "description": "Remaining payment for wedding catering service"
    },
    {
      "id": "payment_009",
      "bookingId": "booking_003_remaining",
      "transactionId": "TXN_DJ_003_REM_2024",
      "employerId": "employer_003",
      "employerName": "Priya & Amit",
      "freelancerId": "freelancer_011",
      "freelancerName": "Sunil Yadav",
      "serviceName": "Wedding DJ & Music",
      "serviceCategory": "DJ",
      "amount": 12000,
      "totalBookingAmount": 18000,
      "paymentType": "remaining",
      "paymentMethod": "Net Banking",
      "paymentStatus": "pending",
      "platformFee": 1200,
      "processingFee": 60,
      "taxes": 216,
      "netAmount": 10524,
      "paymentDate": null,
      "bookingDate": "2024-02-25",
      "location": "Hyderabad, Telangana",
      "paymentGateway": "Razorpay",
      "gatewayTransactionId": null,
      "refundStatus": null,
      "description": "Remaining payment for wedding DJ service"
    },
    {
      "id": "payment_010",
      "bookingId": "booking_005_remaining",
      "transactionId": "TXN_MAGIC_005_REM_2024",
      "employerId": "employer_005",
      "employerName": "Sunita Gupta",
      "freelancerId": "freelancer_021",
      "freelancerName": "Vivek Pandey",
      "serviceName": "Birthday Party Magic Show",
      "serviceCategory": "Magician",
      "amount": 2500,
      "totalBookingAmount": 3500,
      "paymentType": "remaining",
      "paymentMethod": "Debit Card",
      "paymentStatus": "pending",
      "platformFee": 250,
      "processingFee": 20,
      "taxes": 45,
      "netAmount": 2185,
      "paymentDate": null,
      "bookingDate": "2024-03-10",
      "location": "Noida, UP",
      "paymentGateway": "PayU",
      "gatewayTransactionId": null,
      "refundStatus": null
    },
    {
      "id": "payment_011",
      "bookingId": "booking_011",
      "transactionId": "TXN_DJ_011_2024",
      "employerId": "employer_011",
      "employerName": "Delhi University",
      "freelancerId": "freelancer_050",
      "freelancerName": "Rohit Malhotra",
      "serviceName": "College Festival DJ",
      "serviceCategory": "DJ",
      "amount": 15000,
      "totalBookingAmount": 15000,
      "paymentType": "full",
      "paymentMethod": "Net Banking",
      "paymentStatus": "completed",
      "platformFee": 1500,
      "processingFee": 75,
      "taxes": 270,
      "netAmount": 13155,
      "paymentDate": "2024-03-28T14:30:00Z",
      "bookingDate": "2024-04-10",
      "location": "New Delhi",
      "paymentGateway": "Razorpay",
      "gatewayTransactionId": "rzp_011_college_dj",
      "refundStatus": null,
      "description": "Full payment for college festival DJ service"
    },
    {
      "id": "payment_012",
      "bookingId": "booking_012",
      "transactionId": "TXN_MUS_012_2024",
      "employerId": "employer_012",
      "employerName": "Anisha & Karan",
      "freelancerId": "freelancer_055",
      "freelancerName": "Kavita Patel",
      "serviceName": "Wedding Sangeet Performance",
      "serviceCategory": "Musician",
      "amount": 4000,
      "totalBookingAmount": 12000,
      "paymentType": "advance",
      "paymentMethod": "UPI",
      "paymentStatus": "completed",
      "platformFee": 400,
      "processingFee": 30,
      "taxes": 72,
      "netAmount": 3498,
      "paymentDate": "2024-04-02T11:15:00Z",
      "bookingDate": "2024-04-15",
      "location": "Ahmedabad, Gujarat",
      "paymentGateway": "Razorpay",
      "gatewayTransactionId": "rzp_012_sangeet",
      "refundStatus": null,
      "description": "Advance payment for sangeet performance"
    },
    {
      "id": "payment_013",
      "bookingId": "booking_013",
      "transactionId": "TXN_MAGIC_013_2024",
      "employerId": "employer_013",
      "employerName": "Infosys Technologies",
      "freelancerId": "freelancer_060",
      "freelancerName": "Pradeep Kumar",
      "serviceName": "Corporate Event Magic Show",
      "serviceCategory": "Magician",
      "amount": 3000,
      "totalBookingAmount": 10000,
      "paymentType": "advance",
      "paymentMethod": "Credit Card",
      "paymentStatus": "completed",
      "platformFee": 300,
      "processingFee": 25,
      "taxes": 54,
      "netAmount": 2621,
      "paymentDate": "2024-04-07T13:45:00Z",
      "bookingDate": "2024-04-20",
      "location": "Bangalore, Karnataka",
      "paymentGateway": "Stripe",
      "gatewayTransactionId": "strp_013_corporate_magic",
      "refundStatus": null,
      "description": "Advance payment for corporate magic show"
    },
    {
      "id": "payment_014",
      "bookingId": "booking_015",
      "transactionId": "TXN_MEHENDI_015_2024",
      "employerId": "employer_015",
      "employerName": "Sunita Sharma",
      "freelancerId": "freelancer_070",
      "freelancerName": "Asha Kumari",
      "serviceName": "Family Function Mehendi",
      "serviceCategory": "Mehendi Artist",
      "amount": 2000,
      "totalBookingAmount": 6000,
      "paymentType": "advance",
      "paymentMethod": "Debit Card",
      "paymentStatus": "completed",
      "platformFee": 200,
      "processingFee": 15,
      "taxes": 36,
      "netAmount": 1749,
      "paymentDate": "2024-04-17T10:25:00Z",
      "bookingDate": "2024-04-30",
      "location": "Lucknow, UP",
      "paymentGateway": "PayU",
      "gatewayTransactionId": "payu_015_family_mehendi",
      "refundStatus": null,
      "description": "Advance payment for family mehendi service"
    },
    {
      "id": "payment_015",
      "bookingId": "booking_016",
      "transactionId": "TXN_DECOR_016_2024",
      "employerId": "employer_016",
      "employerName": "Amit & Priya",
      "freelancerId": "freelancer_075",
      "freelancerName": "Neha Agarwal",
      "serviceName": "Anniversary Party Decoration",
      "serviceCategory": "Theme Decorator",
      "amount": 15000,
      "totalBookingAmount": 15000,
      "paymentType": "full",
      "paymentMethod": "UPI",
      "paymentStatus": "completed",
      "platformFee": 1500,
      "processingFee": 75,
      "taxes": 270,
      "netAmount": 13155,
      "paymentDate": "2024-04-22T14:10:00Z",
      "bookingDate": "2024-05-05",
      "location": "Gurgaon, Haryana",
      "paymentGateway": "Razorpay",
      "gatewayTransactionId": "rzp_016_anniversary",
      "refundStatus": null,
      "description": "Full payment for anniversary decoration"
    },
    {
      "id": "payment_016",
      "bookingId": "booking_018",
      "transactionId": "TXN_TATTOO_018_2024",
      "employerId": "employer_018",
      "employerName": "Varun Kapoor",
      "freelancerId": "freelancer_085",
      "freelancerName": "Rajat Singh",
      "serviceName": "Memorial Tattoo Design",
      "serviceCategory": "Tattoo Artist",
      "amount": 4000,
      "totalBookingAmount": 12000,
      "paymentType": "advance",
      "paymentMethod": "Credit Card",
      "paymentStatus": "completed",
      "platformFee": 400,
      "processingFee": 30,
      "taxes": 72,
      "netAmount": 3498,
      "paymentDate": "2024-05-02T12:30:00Z",
      "bookingDate": "2024-05-15",
      "location": "Delhi",
      "paymentGateway": "Stripe",
      "gatewayTransactionId": "strp_018_memorial_tattoo",
      "refundStatus": null,
      "description": "Advance payment for memorial tattoo"
    },
    {
      "id": "payment_017",
      "bookingId": "booking_019",
      "transactionId": "TXN_CHEF_019_2024",
      "employerId": "employer_019",
      "employerName": "TechCorp Solutions",
      "freelancerId": "freelancer_090",
      "freelancerName": "Madhuri Jain",
      "serviceName": "Corporate Lunch Catering",
      "serviceCategory": "Chef",
      "amount": 6000,
      "totalBookingAmount": 20000,
      "paymentType": "advance",
      "paymentMethod": "Net Banking",
      "paymentStatus": "completed",
      "platformFee": 600,
      "processingFee": 40,
      "taxes": 108,
      "netAmount": 5252,
      "paymentDate": "2024-05-07T16:45:00Z",
      "bookingDate": "2024-05-20",
      "location": "Hyderabad, Telangana",
      "paymentGateway": "Razorpay",
      "gatewayTransactionId": "rzp_019_corporate_lunch",
      "refundStatus": null,
      "description": "Advance payment for corporate catering"
    },
    {
      "id": "payment_018",
      "bookingId": "booking_017",
      "transactionId": "TXN_BAR_017_2024",
      "employerId": "employer_017",
      "employerName": "Rohit Verma",
      "freelancerId": "freelancer_080",
      "freelancerName": "Suresh Reddy",
      "serviceName": "Birthday Party Bartending",
      "serviceCategory": "Bartender",
      "amount": 8500,
      "totalBookingAmount": 8500,
      "paymentType": "full",
      "paymentMethod": "UPI",
      "paymentStatus": "refunded",
      "platformFee": 850,
      "processingFee": 50,
      "taxes": 153,
      "netAmount": 7447,
      "paymentDate": "2024-04-27T17:30:00Z",
      "bookingDate": "2024-05-10",
      "location": "Mumbai, Maharashtra",
      "paymentGateway": "Razorpay",
      "gatewayTransactionId": "rzp_017_birthday_bar",
      "refundStatus": "refunded",
      "refundDate": "2024-05-03T09:15:00Z",
      "refundAmount": 8500,
      "refundReason": "Client cancelled due to venue change",
      "description": "Full payment for birthday bartending - REFUNDED"
    },
    {
      "id": "payment_019",
      "bookingId": "booking_014",
      "transactionId": "TXN_COMEDY_014_2024",
      "employerId": "employer_014",
      "employerName": "Ravi & Meera",
      "freelancerId": "freelancer_065",
      "freelancerName": "Vikram Joshi",
      "serviceName": "Wedding Reception Comedy",
      "serviceCategory": "Stand-up Comedian",
      "amount": 7500,
      "totalBookingAmount": 7500,
      "paymentType": "cash_on_delivery",
      "paymentMethod": "Cash",
      "paymentStatus": "pending",
      "platformFee": 0,
      "processingFee": 0,
      "taxes": 0,
      "netAmount": 7500,
      "paymentDate": null,
      "bookingDate": "2024-04-25",
      "location": "Goa",
      "paymentGateway": null,
      "gatewayTransactionId": null,
      "refundStatus": null,
      "description": "Cash on delivery for wedding comedy"
    },
    {
      "id": "payment_020",
      "bookingId": "booking_020",
      "transactionId": "TXN_DJ_020_2024",
      "employerId": "employer_020",
      "employerName": "Bank of India",
      "freelancerId": "freelancer_095",
      "freelancerName": "Arjun Malhotra",
      "serviceName": "Retirement Party DJ",
      "serviceCategory": "DJ",
      "amount": 9000,
      "totalBookingAmount": 9000,
      "paymentType": "cash_on_delivery",
      "paymentMethod": "Cash",
      "paymentStatus": "pending",
      "platformFee": 0,
      "processingFee": 0,
      "taxes": 0,
      "netAmount": 9000,
      "paymentDate": null,
      "bookingDate": "2024-05-25",
      "location": "Kolkata, West Bengal",
      "paymentGateway": null,
      "gatewayTransactionId": null,
      "refundStatus": null,
      "description": "Cash on delivery for retirement party DJ"
    }
  ]
}